portmodmigrate/__init__.py
portmodmigrate/datadir.py
portmodmigrate/migrate.py
portmodmigrate-0.2.2.dist-info/LICENSE
portmodmigrate-0.2.2.dist-info/METADATA
portmodmigrate-0.2.2.dist-info/WHEEL
portmodmigrate-0.2.2.dist-info/entry_points.txt
portmodmigrate-0.2.2.dist-info/top_level.txt
portmodmigrate-0.2.2.dist-info/RECORD
