Metadata-Version: 2.1
Name: portmodmigrate
Version: 0.2.2
Summary: A tool to help migrate from manually installed OpenMW mods to Portmod
Home-page: https://gitlab.com/portmod/portmodmigrate
Author: Portmod Authors
License: GPLv3
Platform: UNKNOWN
License-File: LICENSE
Requires-Dist: portmod (>=2.1)
Requires-Dist: fuzzywuzzy
